[
  {
    "vaga_id": "V001",
    "titulo": "Discipulado em Jordania",
    "pais": "jordania",
    "agencia_id": "A001",
    "status": "em_selecao",
    "urgente": "nao",
    "vagas_total": 7,
    "cands_sugestao": 2,
    "cands_sorteio": 0,
    "cands_total": 2,
    "top1_cand_id": "C027",
    "top1_score": 95.0
  },
  {
    "vaga_id": "V002",
    "titulo": "Ti Suporte em Iraque",
    "pais": "iraque",
    "agencia_id": "A004",
    "status": "expirada",
    "urgente": "sim",
    "vagas_total": 9,
    "cands_sugestao": 0,
    "cands_sorteio": 0,
    "cands_total": 0,
    "top1_cand_id": "",
    "top1_score": 0.0
  },
  {
    "vaga_id": "V003",
    "titulo": "Ensino Biblico em Paquistao",
    "pais": "paquistao",
    "agencia_id": "A010",
    "status": "em_selecao",
    "urgente": "sim",
    "vagas_total": 16,
    "cands_sugestao": 0,
    "cands_sorteio": 0,
    "cands_total": 0,
    "top1_cand_id": "",
    "top1_score": 0.0
  },
  {
    "vaga_id": "V004",
    "titulo": "Administracao em Egito",
    "pais": "egito",
    "agencia_id": "A004",
    "status": "rascunho",
    "urgente": "nao",
    "vagas_total": 16,
    "cands_sugestao": 0,
    "cands_sorteio": 0,
    "cands_total": 0,
    "top1_cand_id": "",
    "top1_score": 0.0
  },
  {
    "vaga_id": "V005",
    "titulo": "Ti Suporte em Iraque",
    "pais": "iraque",
    "agencia_id": "A009",
    "status": "expirada",
    "urgente": "nao",
    "vagas_total": 15,
    "cands_sugestao": 0,
    "cands_sorteio": 0,
    "cands_total": 0,
    "top1_cand_id": "",
    "top1_score": 0.0
  },
  {
    "vaga_id": "V006",
    "titulo": "Saude Basica em Quenia",
    "pais": "quenia",
    "agencia_id": "A006",
    "status": "em_selecao",
    "urgente": "nao",
    "vagas_total": 9,
    "cands_sugestao": 1,
    "cands_sorteio": 0,
    "cands_total": 1,
    "top1_cand_id": "C008",
    "top1_score": 95.0
  },
  {
    "vaga_id": "V007",
    "titulo": "Administracao em Brasil",
    "pais": "brasil",
    "agencia_id": "A010",
    "status": "expirada",
    "urgente": "nao",
    "vagas_total": 8,
    "cands_sugestao": 0,
    "cands_sorteio": 0,
    "cands_total": 0,
    "top1_cand_id": "",
    "top1_score": 0.0
  },
  {
    "vaga_id": "V008",
    "titulo": "Primeiros Socorros em Paquistao",
    "pais": "paquistao",
    "agencia_id": "A010",
    "status": "preenchida",
    "urgente": "nao",
    "vagas_total": 13,
    "cands_sugestao": 0,
    "cands_sorteio": 0,
    "cands_total": 0,
    "top1_cand_id": "",
    "top1_score": 0.0
  },
  {
    "vaga_id": "V009",
    "titulo": "Administracao em Paquistao",
    "pais": "paquistao",
    "agencia_id": "A007",
    "status": "em_selecao",
    "urgente": "sim",
    "vagas_total": 5,
    "cands_sugestao": 0,
    "cands_sorteio": 0,
    "cands_total": 0,
    "top1_cand_id": "",
    "top1_score": 0.0
  },
  {
    "vaga_id": "V010",
    "titulo": "Evangelismo em Quenia",
    "pais": "quenia",
    "agencia_id": "A010",
    "status": "publicada",
    "urgente": "nao",
    "vagas_total": 9,
    "cands_sugestao": 1,
    "cands_sorteio": 1,
    "cands_total": 2,
    "top1_cand_id": "C057",
    "top1_score": 97.5
  },
  {
    "vaga_id": "V011",
    "titulo": "Traducao Interpretacao em Egito",
    "pais": "egito",
    "agencia_id": "A009",
    "status": "expirada",
    "urgente": "nao",
    "vagas_total": 16,
    "cands_sugestao": 0,
    "cands_sorteio": 0,
    "cands_total": 0,
    "top1_cand_id": "",
    "top1_score": 0.0
  },
  {
    "vaga_id": "V012",
    "titulo": "Ensino Biblico em Libano",
    "pais": "libano",
    "agencia_id": "A010",
    "status": "rascunho",
    "urgente": "nao",
    "vagas_total": 15,
    "cands_sugestao": 0,
    "cands_sorteio": 0,
    "cands_total": 0,
    "top1_cand_id": "",
    "top1_score": 0.0
  },
  {
    "vaga_id": "V013",
    "titulo": "Administracao em Paquistao",
    "pais": "paquistao",
    "agencia_id": "A006",
    "status": "expirada",
    "urgente": "nao",
    "vagas_total": 16,
    "cands_sugestao": 0,
    "cands_sorteio": 0,
    "cands_total": 0,
    "top1_cand_id": "",
    "top1_score": 0.0
  },
  {
    "vaga_id": "V014",
    "titulo": "Evangelismo em Jordania",
    "pais": "jordania",
    "agencia_id": "A006",
    "status": "rascunho",
    "urgente": "nao",
    "vagas_total": 10,
    "cands_sugestao": 0,
    "cands_sorteio": 0,
    "cands_total": 0,
    "top1_cand_id": "",
    "top1_score": 0.0
  },
  {
    "vaga_id": "V015",
    "titulo": "Traducao Interpretacao em Siria",
    "pais": "siria",
    "agencia_id": "A002",
    "status": "expirada",
    "urgente": "nao",
    "vagas_total": 18,
    "cands_sugestao": 0,
    "cands_sorteio": 0,
    "cands_total": 0,
    "top1_cand_id": "",
    "top1_score": 0.0
  },
  {
    "vaga_id": "V016",
    "titulo": "Primeiros Socorros em Iraque",
    "pais": "iraque",
    "agencia_id": "A009",
    "status": "preenchida",
    "urgente": "nao",
    "vagas_total": 20,
    "cands_sugestao": 0,
    "cands_sorteio": 0,
    "cands_total": 0,
    "top1_cand_id": "",
    "top1_score": 0.0
  },
  {
    "vaga_id": "V017",
    "titulo": "Ti Suporte em Jordania",
    "pais": "jordania",
    "agencia_id": "A010",
    "status": "em_selecao",
    "urgente": "nao",
    "vagas_total": 10,
    "cands_sugestao": 2,
    "cands_sorteio": 0,
    "cands_total": 2,
    "top1_cand_id": "C036",
    "top1_score": 95.0
  },
  {
    "vaga_id": "V018",
    "titulo": "Ensino Biblico em Egito",
    "pais": "egito",
    "agencia_id": "A002",
    "status": "rascunho",
    "urgente": "nao",
    "vagas_total": 13,
    "cands_sugestao": 0,
    "cands_sorteio": 0,
    "cands_total": 0,
    "top1_cand_id": "",
    "top1_score": 0.0
  },
  {
    "vaga_id": "V019",
    "titulo": "Evangelismo em Paquistao",
    "pais": "paquistao",
    "agencia_id": "A001",
    "status": "rascunho",
    "urgente": "nao",
    "vagas_total": 12,
    "cands_sugestao": 0,
    "cands_sorteio": 0,
    "cands_total": 0,
    "top1_cand_id": "",
    "top1_score": 0.0
  },
  {
    "vaga_id": "V020",
    "titulo": "Primeiros Socorros em Brasil",
    "pais": "brasil",
    "agencia_id": "A009",
    "status": "expirada",
    "urgente": "nao",
    "vagas_total": 9,
    "cands_sugestao": 0,
    "cands_sorteio": 0,
    "cands_total": 0,
    "top1_cand_id": "",
    "top1_score": 0.0
  }
]